MANIFEST.in
README.rst
setup.cfg
setup.py
project_rename/__init__.py
project_rename/admin.py
project_rename/apps.py
project_rename/models.py
project_rename/tests.py
project_rename/views.py
project_rename.egg-info/PKG-INFO
project_rename.egg-info/SOURCES.txt
project_rename.egg-info/dependency_links.txt
project_rename.egg-info/top_level.txt
project_rename/management/__init__.py
project_rename/management/commands/__init__.py
project_rename/management/commands/rename.py
project_rename/migrations/__init__.py